kan_gpt/__init__.py
kan_gpt/__main__.py
kan_gpt/base.py
kan_gpt/cli.py
kan_gpt/dataset.py
kan_gpt/download_dataset.py
kan_gpt/model.py
kan_gpt/prompt.py
kan_gpt/settings.py
kan_gpt/sweep.py
kan_gpt/train.py
kan_gpt/efficient_kan/__init__.py
kan_gpt/efficient_kan/model.py
kan_gpt/kan/KAN.py
kan_gpt/kan/KANLayer.py
kan_gpt/kan/LBFGS.py
kan_gpt/kan/Symbolic_KANLayer.py
kan_gpt/kan/__init__.py
kan_gpt/kan/spline.py
kan_gpt/kan/utils.py
kan_gpt/mingpt/__init__.py
kan_gpt/mingpt/bpe.py
kan_gpt/mingpt/model.py
kan_gpt/mingpt/trainer.py
kan_gpt/mingpt/utils.py
kan_gpt-1.2.0.dist-info/LICENSE
kan_gpt-1.2.0.dist-info/METADATA
kan_gpt-1.2.0.dist-info/WHEEL
kan_gpt-1.2.0.dist-info/entry_points.txt
kan_gpt-1.2.0.dist-info/top_level.txt
kan_gpt-1.2.0.dist-info/RECORD
