Metadata-Version: 2.1
Name: kan_gpt
Version: 1.2.0
Summary: Awesome kan_gpt created by AdityaNG
Home-page: https://github.com/AdityaNG/kan-gpt/
Author: AdityaNG
License-File: LICENSE
Requires-Dist: matplotlib>=3.6.2
Requires-Dist: numpy>=1.24.4
Requires-Dist: scikit-learn>=1.1.3
Requires-Dist: setuptools>=65.5.0
Requires-Dist: sympy>=1.11.1
Requires-Dist: torch>=2.0.1
Requires-Dist: tqdm>=4.66.2
Requires-Dist: pandas>=2.0.3
Requires-Dist: requests>=2.31.0
Requires-Dist: transformers>=4.40.1
Requires-Dist: wandb>=0.16.6
Requires-Dist: torchvision
Provides-Extra: test
Requires-Dist: pytest; extra == "test"
Requires-Dist: coverage; extra == "test"
Requires-Dist: flake8; extra == "test"
Requires-Dist: black; extra == "test"
Requires-Dist: isort; extra == "test"
Requires-Dist: pytest-cov; extra == "test"
Requires-Dist: mypy; extra == "test"
Requires-Dist: gitchangelog; extra == "test"
Requires-Dist: mkdocs; extra == "test"
Requires-Dist: lark; extra == "test"
Requires-Dist: types-requests; extra == "test"
Requires-Dist: requests-mock; extra == "test"
